{
  "artwork_name": "幸運を運ぶナナホシテントウ",
  "artwork_description": "てんとう虫は漢字で「天道虫」と書きます。太陽に向かって上に飛び上がることからその名が付けられ、神の使いとして縁起の良い虫とされています。太陽はやる気と生命の源であるエネルギーを与えるとされています。また幸運のモチーフであるクローバーと合わせました。",
  "wood_name": "【王室御用達 】 キングウッド",
  "wood_variation": "",
  "catch_copy": "王室御用達",
  "blog_url": "https://kinmokuseijp.blog/king-wood/",
  "price": "5300",
  "scraped_from_title": "【王室御用達 】 キングウッド ドッグタグ 木象嵌 幸運を運ぶナナホシテントウ",
  "variants": [
    {
      "wood_name": "【王室御用達 】 キングウッド",
      "wood_variation": "",
      "price": "5300",
      "scraped_from_title": "【王室御用達 】 キングウッド ドッグタグ 木象嵌 幸運を運ぶナナホシテントウ"
    },
    {
      "wood_name": "【音楽業界屈指の銘木】 ハカランダ",
      "wood_variation": "",
      "price": "4500",
      "scraped_from_title": "【音楽業界屈指の銘木】 ハカランダ ドッグタグ 象嵌 幸運を運ぶナナホシテントウ"
    },
    {
      "wood_name": "【音楽業界屈指の銘木】 ハカランダ",
      "wood_variation": "",
      "price": "5300",
      "scraped_from_title": "【音楽業界屈指の銘木】 ハカランダ ドッグタグ 象嵌 幸運を運ぶナナホシテントウ"
    },
    {
      "wood_name": "【音楽業界屈指の銘木】 ハカランダ",
      "wood_variation": "",
      "price": "4500",
      "scraped_from_title": "※【音楽業界屈指の銘木】 ハカランダ ドッグタグ 象嵌 幸運を運ぶナナホシテントウ"
    },
    {
      "wood_name": "【21世紀最高峰の材】 サイアミーズローズウッド マイクロカーリー",
      "wood_variation": "",
      "price": "5500",
      "scraped_from_title": "【21世紀最高峰の材】 サイアミーズローズウッド マイクロカーリー ドッグタグ 象嵌 幸運を運ぶナナホシテントウ"
    },
    {
      "wood_name": "【 エスニックなローズウッド 】 ココボロ",
      "wood_variation": "",
      "price": "4500",
      "scraped_from_title": "【 エスニックなローズウッド 】 ココボロ ドッグタグ 象嵌 幸運を運ぶナナホシテントウ"
    },
    {
      "wood_name": "【唐木三大銘木】 紫檀 (ソノケリン)",
      "wood_variation": "",
      "price": "4500",
      "scraped_from_title": "【唐木三大銘木】 紫檀 (ソノケリン) ドッグタグ 象嵌 幸運を運ぶナナホシテントウ"
    },
    {
      "wood_name": "【砂漠の宝石】 デザートアイアンウッド",
      "wood_variation": "",
      "price": "4500",
      "scraped_from_title": "【砂漠の宝石】 デザートアイアンウッド ドッグタグ 象嵌 幸運を運ぶナナホシテントウ"
    }
  ]
}